tpdne/__init__.py
tpdne_py-0.0.5.dist-info/LICENSE
tpdne_py-0.0.5.dist-info/METADATA
tpdne_py-0.0.5.dist-info/WHEEL
tpdne_py-0.0.5.dist-info/top_level.txt
tpdne_py-0.0.5.dist-info/RECORD
