Metadata-Version: 2.1
Name: tpdne-py
Version: 0.0.5
Summary: a very simple wrapper around requests/aiohttp for thispersondoesnotexist.com
Home-page: https://github.com/anytarseir67/tpdne-py
Author: anytarseir67
Author-email: 
License: GPLv3
Platform: UNKNOWN
License-File: LICENSE
Requires-Dist: aiohttp
Requires-Dist: requests
